setup.py
rpi_gpio_http/__init__.py
rpi_gpio_http/app.py
rpi_gpio_http/channel.py
rpi_gpio_http/config.py
rpi_gpio_http/controllers.py
rpi_gpio_http.egg-info/PKG-INFO
rpi_gpio_http.egg-info/SOURCES.txt
rpi_gpio_http.egg-info/dependency_links.txt
rpi_gpio_http.egg-info/requires.txt
rpi_gpio_http.egg-info/top_level.txt