Metadata-Version: 1.0
Name: rpi-gpio-http
Version: 1.1.0
Summary: HTTP interface for Raspberry Pi GPIO
Home-page: https://github.com/voidpp/rpi-gpio-http.git
Author: Lajos Santa
Author-email: santa.lajos@coldline.hu
License: UNKNOWN
Platform: UNKNOWN
